{"frames": [

{
	"filename": "attack1.png",
	"frame": {"x":0,"y":0,"w":100,"h":100},
	"rotated": false,
	"trimmed": false,
	"spriteSourceSize": {"x":0,"y":0,"w":100,"h":100},
	"sourceSize": {"w":100,"h":100}
},
{
	"filename": "attack2.png",
	"frame": {"x":100,"y":0,"w":100,"h":100},
	"rotated": false,
	"trimmed": false,
	"spriteSourceSize": {"x":0,"y":0,"w":100,"h":100},
	"sourceSize": {"w":100,"h":100}
},
{
	"filename": "Pbackwalk1.png",
	"frame": {"x":200,"y":0,"w":100,"h":100},
	"rotated": false,
	"trimmed": false,
	"spriteSourceSize": {"x":0,"y":0,"w":100,"h":100},
	"sourceSize": {"w":100,"h":100}
},
{
	"filename": "Pbackwalk2.png",
	"frame": {"x":300,"y":0,"w":100,"h":100},
	"rotated": false,
	"trimmed": false,
	"spriteSourceSize": {"x":0,"y":0,"w":100,"h":100},
	"sourceSize": {"w":100,"h":100}
},
{
	"filename": "Pbackwalk3.png",
	"frame": {"x":400,"y":0,"w":100,"h":100},
	"rotated": false,
	"trimmed": false,
	"spriteSourceSize": {"x":0,"y":0,"w":100,"h":100},
	"sourceSize": {"w":100,"h":100}
},
{
	"filename": "Pfrontwalk1.png",
	"frame": {"x":500,"y":0,"w":100,"h":100},
	"rotated": false,
	"trimmed": false,
	"spriteSourceSize": {"x":0,"y":0,"w":100,"h":100},
	"sourceSize": {"w":100,"h":100}
},
{
	"filename": "Pfrontwalk2.png",
	"frame": {"x":600,"y":0,"w":100,"h":100},
	"rotated": false,
	"trimmed": false,
	"spriteSourceSize": {"x":0,"y":0,"w":100,"h":100},
	"sourceSize": {"w":100,"h":100}
},
{
	"filename": "Pfrontwalk3.png",
	"frame": {"x":700,"y":0,"w":100,"h":100},
	"rotated": false,
	"trimmed": false,
	"spriteSourceSize": {"x":0,"y":0,"w":100,"h":100},
	"sourceSize": {"w":100,"h":100}
},
{
	"filename": "Pleftwalk1.png",
	"frame": {"x":800,"y":0,"w":100,"h":100},
	"rotated": false,
	"trimmed": false,
	"spriteSourceSize": {"x":0,"y":0,"w":100,"h":100},
	"sourceSize": {"w":100,"h":100}
},
{
	"filename": "Pleftwalk2.png",
	"frame": {"x":900,"y":0,"w":100,"h":100},
	"rotated": false,
	"trimmed": false,
	"spriteSourceSize": {"x":0,"y":0,"w":100,"h":100},
	"sourceSize": {"w":100,"h":100}
},
{
	"filename": "Pleftwalk3.png",
	"frame": {"x":1000,"y":0,"w":100,"h":100},
	"rotated": false,
	"trimmed": false,
	"spriteSourceSize": {"x":0,"y":0,"w":100,"h":100},
	"sourceSize": {"w":100,"h":100}
},
{
	"filename": "Pleftwalk4.png",
	"frame": {"x":1100,"y":0,"w":100,"h":100},
	"rotated": false,
	"trimmed": false,
	"spriteSourceSize": {"x":0,"y":0,"w":100,"h":100},
	"sourceSize": {"w":100,"h":100}
},
{
	"filename": "Prightwalk1.png",
	"frame": {"x":1200,"y":0,"w":100,"h":100},
	"rotated": false,
	"trimmed": false,
	"spriteSourceSize": {"x":0,"y":0,"w":100,"h":100},
	"sourceSize": {"w":100,"h":100}
},
{
	"filename": "Prightwalk2.png",
	"frame": {"x":1300,"y":0,"w":100,"h":100},
	"rotated": false,
	"trimmed": false,
	"spriteSourceSize": {"x":0,"y":0,"w":100,"h":100},
	"sourceSize": {"w":100,"h":100}
},
{
	"filename": "Prightwalk3.png",
	"frame": {"x":1400,"y":0,"w":100,"h":100},
	"rotated": false,
	"trimmed": false,
	"spriteSourceSize": {"x":0,"y":0,"w":100,"h":100},
	"sourceSize": {"w":100,"h":100}
},
{
	"filename": "Prightwalk4.png",
	"frame": {"x":1500,"y":0,"w":100,"h":100},
	"rotated": false,
	"trimmed": false,
	"spriteSourceSize": {"x":0,"y":0,"w":100,"h":100},
	"sourceSize": {"w":100,"h":100}
}],
"meta": {
	"app": "https://www.codeandweb.com/texturepacker",
	"version": "1.0",
	"image": "player.png",
	"format": "RGBA8888",
	"size": {"w":1600,"h":100},
	"scale": "1",
	"smartupdate": "$TexturePacker:SmartUpdate:136c5239aaa7cfd7ebe265c4854071bc:9dea753ee6f252042fe8e6a9273fa106:86d5339b780aedd87b35e2b7c0a7e11b$"
}
}
